hugpi/__init__.py
hugpi/features/__init__.py
hugpi/features/_hugpi.py
hugpi/features/chat.py
hugpi/model/__init__.py
hugpi/model/api/__init__.py
hugpi/model/api/_chatbot.py
hugpi/model/api/_client.py
hugpi/model/api/_models.py
hugpi/model/api/_tool_calling.py
hugpi/model/api/resources/__init__.py
hugpi/model/api/resources/messages.py
hugpi/model/api/types/__init__.py
hugpi/model/api/types/_message.py
hugpi/model/api/types/_model_types.py
hugpi/model/api/types/content_block.py
hugpi/model/api/types/text_block.py
hugpi/model/api/types/text_block_param.py
hugpi/model/api/types/tool_param.py
hugpi/model/api/types/tool_result_block_param.py
hugpi/model/api/types/tool_use_block.py
hugpi/model/api/types/tool_use_block_param.py
hugpi/model/api/types/usage.py
hugpi/model/base/__init__.py
hugpi/model/base/_base_huggy_chat.py
hugpi/model/base/_base_llm.py
hugpi/model/base/_base_login.py
hugpi/model/base/_hf_chatbot_custom.py
hugpi/model/server/__init__.py
hugpi/model/server/hugpi_api.py
hugpi/model/server/simple_streamlit_app.py
hugpi/model/utils/__init__.py
hugpi/model/utils/_print_text.py
hugpi/model/utils/const.py
hugpi_features-0.8.0.dist-info/METADATA
hugpi_features-0.8.0.dist-info/WHEEL
hugpi_features-0.8.0.dist-info/top_level.txt
hugpi_features-0.8.0.dist-info/RECORD
