Metadata-Version: 2.1
Name: hugpi-features
Version: 0.8.0
Summary: Hugging Face chat based python library
Author-email: Kammari santhosh <your.email@example.com>
Project-URL: Homepage, https://github.com/yourusername
Project-URL: Bug Tracker, https://github.com/yourusername
Classifier: Programming Language :: Python :: 3
Classifier: License :: OSI Approved :: MIT License
Classifier: Operating System :: OS Independent
Requires-Python: >=3.11
Requires-Dist: langchain-core
Requires-Dist: pydantic
Requires-Dist: transformers
Requires-Dist: hugchat
Requires-Dist: lxml-html-clean
Requires-Dist: pyqt5
Requires-Dist: pyopengenai
Requires-Dist: phidata
